{
  "content": "",
  "tts": false,
  "embeds": [
    {
      "id": 584068271,
      "description": "⠀\n**Ваш Тикет / Ваша Апелляция.**",
      "fields": [],
      "color": 10987479,
      "image": {
        "url": "https://i.ibb.co/26ySjnr/filler.png"
      }
    },
    {
      "id": 71514909,
      "description": "### **Закрыто!**\n⠀\n> Ваш тикет был закрыт, проблема/вопрос решён, или решения не найдено.",
      "fields": [],
      "color": 10987479,
      "image": {
        "url": "https://i.ibb.co/26ySjnr/filler.png"
      }
    },
    {
      "id": 184215895,
      "description": "",
      "fields": [],
      "color": 10987479,
      "image": {
        "url": "https://i.ibb.co/M7DtSqd/banner.png"
      }
    }
  ],
  "components": [],
  "actions": {}
}